tv/bram/pal_bram_loader.vhd
library ieee;
use ieee.std_logic_1164.all;
use ieee.numeric_std.all;

-- pal_bram_loader
-- ===========================================================================
-- Reads 1-bit pixels from a FIFO and writes them sequentially to the BRAM
-- write port of pal_tv_bram_top (addresses 0 .. TOTAL_PX-1).
--
-- Typical flow
-- ------------
--   1. Host dumps all TOTAL_PX pixels into the FIFO at any speed (Boolean
--      elements: 0=black, 1=white; row 0 first, row 575 last).
--   2. Host sets start = TRUE for at least one clock cycle.
--   3. This core drains the FIFO at full FPGA clock speed and writes every
--      pixel to pal_tv_bram_top's BRAM write port.
--        At 10 MHz : 299 520 pixels → ~60 ms   (1 pixel per 2 clocks)
--        At 40 MHz : 299 520 pixels → ~15 ms
--   4. done = TRUE when the last pixel has been written.
--      Set pal_tv_bram_top sel = x"04" and release rst to start playback.
--
-- Re-trigger: assert start again (while done is HIGH or after it) to reload.
-- Stall-safe: if FIFO runs empty mid-load, this core pauses and resumes
--             automatically when more data arrives.
--
-- FIFO timing
-- -----------
-- Assumes 1-clock read latency:
--   Cycle N   : fifo_rd = '1' (read request issued to FIFO)
--   Cycle N+1 : fifo_data = valid pixel (registered output of FIFO)
-- This matches the LabVIEW FPGA SCTL inter-node pipeline delay for a
-- Target-Scoped or DMA FIFO accessed inside a Single-Cycle Timed Loop.
--
-- LabVIEW FPGA wiring (inside SCTL)
-- -----------------------------------
--   fifo_rd   (output, Boolean) ─► FIFO "Read"    terminal
--   fifo_data (input,  Boolean) ◄─ FIFO "Element" terminal   (1-cycle latency)
--   fifo_empty(input,  Boolean) ◄─ FIFO "Empty"   terminal
--
--   bram_wr_en   ─► pal_tv_bram_top  bram_wr_en
--   bram_wr_addr ─► pal_tv_bram_top  bram_wr_addr  (U32, lower 19 bits)
--   bram_wr_data ─► pal_tv_bram_top  bram_wr_data
--
--   start ◄─ host control register (Boolean)
--   done  ─► host status  register (Boolean)
--   busy  ─► host status  register (Boolean)
-- ===========================================================================

entity pal_bram_loader is
  generic (
    TOTAL_PX  : integer := 299520;  -- 520 * 576 pixels (full PAL frame)
    ADDR_BITS : integer := 19       -- address width  (2^19 = 524288 > 299520)
  );
  port (
    clk  : in  std_logic;
    rst  : in  std_logic;

    -- -----------------------------------------------------------------------
    -- Host control
    -- -----------------------------------------------------------------------
    start : in  std_logic;   -- hold HIGH ≥1 clock when FIFO is fully loaded
    done  : out std_logic;   -- HIGH when all TOTAL_PX pixels written to BRAM
    busy  : out std_logic;   -- HIGH while loading is in progress

    -- -----------------------------------------------------------------------
    -- FIFO read interface  (Boolean per pixel, 1-clock read latency)
    -- -----------------------------------------------------------------------
    fifo_data  : in  std_logic;  -- pixel (0=black, 1=white); valid 1 clk after fifo_rd
    fifo_empty : in  std_logic;  -- '1' when FIFO has no data
    fifo_rd    : out std_logic;  -- pulse '1' to consume one element (data valid next clk)

    -- -----------------------------------------------------------------------
    -- BRAM write port  ─►  connect directly to pal_tv_bram_top
    -- -----------------------------------------------------------------------
    bram_wr_en   : out std_logic;
    bram_wr_addr : out std_logic_vector(ADDR_BITS - 1 downto 0);
    bram_wr_data : out std_logic
  );
end entity pal_bram_loader;

architecture rtl of pal_bram_loader is

  type state_t is (S_IDLE, S_LOADING, S_DONE);
  signal state : state_t := S_IDLE;

  -- Number of pixels written to BRAM so far
  signal writes_done  : integer range 0 to TOTAL_PX := 0;

  -- '1' while a FIFO read is in flight (issued but data not yet received)
  signal read_pending : std_logic := '0';

  -- Internal drives
  signal fifo_rd_i : std_logic := '0';  -- drives fifo_rd port
  signal fifo_rd_r : std_logic := '0';  -- registered fifo_rd_i: '1' → data valid

begin

  fifo_rd <= fifo_rd_i;

  -- =========================================================================
  -- Main process
  -- Uses VARIABLES for read_pending and writes_done so that within a single
  -- clock cycle the "process response → issue next read" sequence can observe
  -- the just-updated values.  This prevents spurious reads at FIFO boundaries.
  -- =========================================================================
  process(clk)
    variable pend_v   : std_logic;
    variable writes_v : integer range 0 to TOTAL_PX;
  begin
    if rising_edge(clk) then

      -- Latch current signal values into working variables
      pend_v   := read_pending;
      writes_v := writes_done;

      -- Default pulse outputs
      fifo_rd_i  <= '0';
      bram_wr_en <= '0';

      -- Pipeline: '1' next cycle means fifo_data is valid
      fifo_rd_r <= fifo_rd_i;

      -- ----------------------------------------------------------------
      -- Reset
      -- ----------------------------------------------------------------
      if rst = '1' then
        state        <= S_IDLE;
        writes_done  <= 0;
        read_pending <= '0';
        done         <= '0';
        busy         <= '0';
        fifo_rd_r    <= '0';

      else
        case state is

          -- --------------------------------------------------------------
          -- IDLE: wait for host start signal
          -- --------------------------------------------------------------
          when S_IDLE =>
            done         <= '0';
            busy         <= '0';
            writes_v     := 0;
            pend_v       := '0';
            if start = '1' then
              state <= S_LOADING;
              busy  <= '1';
            end if;

          -- --------------------------------------------------------------
          -- LOADING: drain FIFO → write BRAM
          --
          -- Two steps execute within a SINGLE clock cycle using variables:
          --   Step 1: if fifo_rd_r='1', write the pixel that arrived this
          --           cycle; clear pending flag.
          --   Step 2: if no read pending, FIFO not empty, and pixels remain,
          --           issue the next read.
          -- This overlapping avoids stalls between consecutive reads.
          -- --------------------------------------------------------------
          when S_LOADING =>
            busy <= '1';

            -- Step 1 – process FIFO response (data valid this cycle)
            if fifo_rd_r = '1' then
              bram_wr_en   <= '1';
              bram_wr_data <= fifo_data;
              bram_wr_addr <= std_logic_vector(to_unsigned(writes_v, ADDR_BITS));
              writes_v     := writes_v + 1;   -- update variable immediately
              pend_v       := '0';            -- read_pending cleared
              if writes_v = TOTAL_PX then     -- uses UPDATED writes_v
                state <= S_DONE;
              end if;
            end if;

            -- Step 2 – issue next FIFO read if possible (uses UPDATED variables)
            if pend_v = '0' and fifo_empty = '0' and writes_v < TOTAL_PX then
              fifo_rd_i <= '1';
              pend_v    := '1';
            end if;

            -- Commit variables back to signals
            writes_done  <= writes_v;
            read_pending <= pend_v;

          -- --------------------------------------------------------------
          -- DONE: hold done flag; re-trigger supported
          -- --------------------------------------------------------------
          when S_DONE =>
            busy         <= '0';
            done         <= '1';
            pend_v       := '0';
            read_pending <= '0';
            if start = '1' then
              state       <= S_LOADING;
              done        <= '0';
              busy        <= '1';
              writes_v    := 0;
              writes_done <= 0;
            end if;

        end case;
      end if;
    end if;
  end process;

end architecture rtl;

tv/bram/tb_pal_bram_loader.vhd
library ieee;
use ieee.std_logic_1164.all;
use ieee.numeric_std.all;

-- Testbench for pal_bram_loader
-- ===========================================================================
-- Tests three scenarios:
--   Test 1 – Normal   : FIFO fully pre-loaded → start → done
--   Test 2 – Stall    : FIFO starts with 3 of 8 pixels; rest arrive mid-load
--   Test 3 – Retrigger: Second frame loaded after done, without reset
--
-- FIFO model: 1-clock read latency (registered output).
-- Checker verifies every BRAM write (address + data) across all three tests.
-- ===========================================================================

entity tb_pal_bram_loader is
end entity tb_pal_bram_loader;

architecture sim of tb_pal_bram_loader is

  -- Small frame for fast simulation (change to 299520/19 for full PAL)
  constant TOTAL_PX   : integer := 8;
  constant ADDR_BITS  : integer := 4;
  constant CLK_PERIOD : time    := 10 ns;

  signal clk        : std_logic := '0';
  signal rst        : std_logic := '1';
  signal start      : std_logic := '0';
  signal done       : std_logic;
  signal busy       : std_logic;
  signal fifo_data  : std_logic;
  signal fifo_empty : std_logic;
  signal fifo_rd    : std_logic;
  signal bram_wr_en   : std_logic;
  signal bram_wr_addr : std_logic_vector(ADDR_BITS - 1 downto 0);
  signal bram_wr_data : std_logic;

  -- -------------------------------------------------------------------------
  -- FIFO model  (depth 16, push from testbench, pop from loader)
  -- 1-clock read latency: data on fifo_out is valid ONE cycle after fifo_rd='1'
  -- -------------------------------------------------------------------------
  constant FIFO_DEPTH : integer := 16;
  type fifo_mem_t is array (0 to FIFO_DEPTH - 1) of std_logic;

  signal fifo_mem    : fifo_mem_t := (others => '0');
  signal fifo_wr_ptr : integer range 0 to FIFO_DEPTH - 1 := 0;
  signal fifo_rd_ptr : integer range 0 to FIFO_DEPTH - 1 := 0;
  signal fifo_count  : integer range 0 to FIFO_DEPTH     := 0;
  signal fifo_out    : std_logic := '0';  -- registered FIFO output

  -- Push interface driven by testbench stimulus
  signal tb_push_en   : std_logic := '0';
  signal tb_push_data : std_logic := '0';

  -- Test patterns (8 pixels each)
  type pattern_t is array (0 to TOTAL_PX - 1) of std_logic;
  constant PATTERN_A : pattern_t := ('1','0','1','0','1','1','0','1');
  constant PATTERN_B : pattern_t := ('0','1','0','1','0','0','1','0');  -- inverted A

begin

  clk <= not clk after CLK_PERIOD / 2;

  -- -------------------------------------------------------------------------
  -- UUT
  -- -------------------------------------------------------------------------
  uut : entity work.pal_bram_loader
    generic map (TOTAL_PX => TOTAL_PX, ADDR_BITS => ADDR_BITS)
    port map (
      clk          => clk,
      rst          => rst,
      start        => start,
      done         => done,
      busy         => busy,
      fifo_data    => fifo_out,    -- registered FIFO output (1-cycle latency)
      fifo_empty   => fifo_empty,
      fifo_rd      => fifo_rd,
      bram_wr_en   => bram_wr_en,
      bram_wr_addr => bram_wr_addr,
      bram_wr_data => bram_wr_data
    );

  fifo_empty <= '1' when fifo_count = 0 else '0';

  -- -------------------------------------------------------------------------
  -- FIFO model: synchronous write (push) and registered read (pop)
  -- Uses a VARIABLE for count so simultaneous push+pop keeps count unchanged.
  -- -------------------------------------------------------------------------
  process(clk)
    variable count_v : integer range 0 to FIFO_DEPTH := 0;
  begin
    if rising_edge(clk) then
      count_v := fifo_count;

      -- Push (testbench → FIFO)
      if tb_push_en = '1' and count_v < FIFO_DEPTH then
        fifo_mem(fifo_wr_ptr) <= tb_push_data;
        fifo_wr_ptr           <= (fifo_wr_ptr + 1) mod FIFO_DEPTH;
        count_v               := count_v + 1;
      end if;

      -- Pop (loader → FIFO): latch current head, advance pointer
      -- Data appears on fifo_out ONE cycle after fifo_rd='1'
      if fifo_rd = '1' and count_v > 0 then
        fifo_out    <= fifo_mem(fifo_rd_ptr);
        fifo_rd_ptr <= (fifo_rd_ptr + 1) mod FIFO_DEPTH;
        count_v     := count_v - 1;
      end if;

      fifo_count <= count_v;
    end if;
  end process;

  -- =========================================================================
  -- Stimulus process
  -- =========================================================================
  process
    -- Push one pixel into FIFO, consume one clock
    procedure push(val : std_logic) is
    begin
      tb_push_data <= val;
      tb_push_en   <= '1';
      wait until rising_edge(clk);
      tb_push_en   <= '0';
    end procedure;

    -- Pulse start for one clock
    procedure trigger is
    begin
      start <= '1';
      wait until rising_edge(clk);
      start <= '0';
    end procedure;

  begin
    -- Release reset
    rst <= '1';
    wait for 5 * CLK_PERIOD;
    rst <= '0';
    wait until rising_edge(clk);

    -- =========================================================================
    -- Test 1: Normal load
    --   Fill FIFO with all 8 pixels, then trigger.
    -- =========================================================================
    report "--- Test 1: Normal load ---" severity note;
    for i in 0 to TOTAL_PX - 1 loop
      push(PATTERN_A(i));
    end loop;
    trigger;
    wait until done = '1';
    assert busy = '0'
      report "Test1: busy should be LOW when done" severity error;
    wait for CLK_PERIOD;
    report "--- Test 1 complete ---" severity note;

    -- =========================================================================
    -- Test 2: Stall — only first 3 pixels in FIFO at trigger time
    --   Loader will stall at pixel 3; remaining pixels arrive one by one.
    -- =========================================================================
    report "--- Test 2: Stall test ---" severity note;
    push(PATTERN_B(0));
    push(PATTERN_B(1));
    push(PATTERN_B(2));
    trigger;

    -- Wait a few clocks so the loader drains those 3 and stalls
    wait for 10 * CLK_PERIOD;

    -- Feed remaining pixels with gaps (simulating slow host)
    for i in 3 to TOTAL_PX - 1 loop
      push(PATTERN_B(i));
      wait for 4 * CLK_PERIOD;
    end loop;

    wait until done = '1';
    report "--- Test 2 complete (stall handled) ---" severity note;
    wait for CLK_PERIOD;

    -- =========================================================================
    -- Test 3: Re-trigger — load a new frame without reset
    -- =========================================================================
    report "--- Test 3: Re-trigger ---" severity note;
    for i in 0 to TOTAL_PX - 1 loop
      push(PATTERN_A(i));
    end loop;
    trigger;
    wait until done = '1';
    report "--- Test 3 complete ---" severity note;
    wait for 3 * CLK_PERIOD;

    report "=== All tests PASSED ===" severity note;
    std.env.finish;
  end process;

  -- =========================================================================
  -- Checker process: verifies EVERY BRAM write across all three tests
  -- Expected sequence: Test1=PATTERN_A, Test2=PATTERN_B, Test3=PATTERN_A
  -- =========================================================================
  process
    variable got_addr : integer;
    variable got_data : std_logic;

    type full_t is array (0 to 3 * TOTAL_PX - 1) of std_logic;
    constant EXPECTED : full_t := (
      -- Test 1: PATTERN_A
      '1','0','1','0','1','1','0','1',
      -- Test 2: PATTERN_B
      '0','1','0','1','0','0','1','0',
      -- Test 3: PATTERN_A
      '1','0','1','0','1','1','0','1'
    );
  begin
    wait until rst = '0';

    for i in 0 to 3 * TOTAL_PX - 1 loop
      wait until rising_edge(clk) and bram_wr_en = '1';
      got_addr := to_integer(unsigned(bram_wr_addr));
      got_data := bram_wr_data;

      assert got_addr = (i mod TOTAL_PX)
        report "FAIL write #" & integer'image(i) &
               " addr: exp=" & integer'image(i mod TOTAL_PX) &
               " got=" & integer'image(got_addr) severity error;

      assert got_data = EXPECTED(i)
        report "FAIL write #" & integer'image(i) &
               " addr=" & integer'image(got_addr) &
               ": exp=" & std_logic'image(EXPECTED(i)) &
               " got=" & std_logic'image(got_data) severity error;
    end loop;

    report "=== Checker: all " & integer'image(3 * TOTAL_PX) &
           " writes correct ===" severity note;
    wait;
  end process;

end architecture sim;

tools/sim_out/bram_loader.vcd
$date
  Sun May 24 15:29:23 2026
$end
$version
  GHDL v0
$end
$timescale
  1 fs
$end
$scope module standard $end
$upscope $end
$scope module textio $end
$upscope $end
$scope module std_logic_1164 $end
$upscope $end
$scope module numeric_std $end
$upscope $end
$scope module env $end
$upscope $end
$scope module tb_pal_bram_loader $end
$var reg 1 ! clk $end
$var reg 1 " rst $end
$var reg 1 # start $end
$var reg 1 $ done $end
$var reg 1 % busy $end
$var reg 1 & fifo_data $end
$var reg 1 ' fifo_empty $end
$var reg 1 ( fifo_rd $end
$var reg 1 ) bram_wr_en $end
$var reg 4 * bram_wr_addr[3:0] $end
$var reg 1 + bram_wr_data $end
$var reg 16 , fifo_mem[0:15] $end
$var integer 32 - fifo_wr_ptr $end
$var integer 32 . fifo_rd_ptr $end
$var integer 32 / fifo_count $end
$var reg 1 0 fifo_out $end
$var reg 1 1 tb_push_en $end
$var reg 1 2 tb_push_data $end
$scope module uut $end
$var reg 1 3 clk $end
$var reg 1 4 rst $end
$var reg 1 5 start $end
$var reg 1 6 done $end
$var reg 1 7 busy $end
$var reg 1 8 fifo_data $end
$var reg 1 9 fifo_empty $end
$var reg 1 : fifo_rd $end
$var reg 1 ; bram_wr_en $end
$var reg 4 < bram_wr_addr[3:0] $end
$var reg 1 = bram_wr_data $end
$comment state is not handled $end
$var integer 32 > writes_done $end
$var reg 1 ? read_pending $end
$var reg 1 @ fifo_rd_i $end
$var reg 1 A fifo_rd_r $end
$upscope $end
$upscope $end
$enddefinitions $end
#0
0!
1"
0#
U$
U%
U&
1'
0(
U)
bUUUU *
U+
b0000000000000000 ,
b0 -
b0 .
b0 /
00
01
02
03
14
05
U6
U7
08
19
0:
U;
bUUUU <
U=
b0 >
0?
0@
0A
#5000000
1!
0$
0%
0)
13
06
07
0;
#10000000
0!
03
#15000000
1!
13
#20000000
0!
03
#25000000
1!
13
#30000000
0!
03
#35000000
1!
13
#40000000
0!
03
#45000000
1!
13
#50000000
0!
0"
03
04
#55000000
1!
11
12
13
#60000000
0!
03
#65000000
1!
0'
b1000000000000000 ,
b1 -
b1 /
02
13
09
#70000000
0!
03
#75000000
1!
b10 -
b10 /
12
13
#80000000
0!
03
#85000000
1!
b1010000000000000 ,
b11 -
b11 /
02
13
#90000000
0!
03
#95000000
1!
b100 -
b100 /
12
13
#100000000
0!
03
#105000000
1!
b1010100000000000 ,
b101 -
b101 /
13
#110000000
0!
03
#115000000
1!
b1010110000000000 ,
b110 -
b110 /
02
13
#120000000
0!
03
#125000000
1!
b111 -
b111 /
12
13
#130000000
0!
03
#135000000
1!
1#
b1010110100000000 ,
b1000 -
b1000 /
01
13
15
#140000000
0!
03
#145000000
1!
0#
1%
13
05
17
#150000000
0!
03
#155000000
1!
1(
13
1:
1?
1@
#160000000
0!
03
#165000000
1!
0(
b1 .
b111 /
10
13
18
0:
0@
1A
#170000000
0!
03
#175000000
1!
1(
1)
b0000 *
1+
13
1:
1;
b0000 <
1=
b1 >
1@
0A
#180000000
0!
03
#185000000
1!
0(
0)
b10 .
b110 /
00
13
08
0:
0;
0@
1A
#190000000
0!
03
#195000000
1!
1(
1)
b0001 *
0+
13
1:
1;
b0001 <
0=
b10 >
1@
0A
#200000000
0!
03
#205000000
1!
0(
0)
b11 .
b101 /
10
13
18
0:
0;
0@
1A
#210000000
0!
03
#215000000
1!
1(
1)
b0010 *
1+
13
1:
1;
b0010 <
1=
b11 >
1@
0A
#220000000
0!
03
#225000000
1!
0(
0)
b100 .
b100 /
00
13
08
0:
0;
0@
1A
#230000000
0!
03
#235000000
1!
1(
1)
b0011 *
0+
13
1:
1;
b0011 <
0=
b100 >
1@
0A
#240000000
0!
03
#245000000
1!
0(
0)
b101 .
b11 /
10
13
18
0:
0;
0@
1A
#250000000
0!
03
#255000000
1!
1(
1)
b0100 *
1+
13
1:
1;
b0100 <
1=
b101 >
1@
0A
#260000000
0!
03
#265000000
1!
0(
0)
b110 .
b10 /
13
0:
0;
0@
1A
#270000000
0!
03
#275000000
1!
1(
1)
b0101 *
13
1:
1;
b0101 <
b110 >
1@
0A
#280000000
0!
03
#285000000
1!
0(
0)
b111 .
b1 /
00
13
08
0:
0;
0@
1A
#290000000
0!
03
#295000000
1!
1(
1)
b0110 *
0+
13
1:
1;
b0110 <
0=
b111 >
1@
0A
#300000000
0!
03
#305000000
1!
1'
0(
0)
b1000 .
b0 /
10
13
18
19
0:
0;
0@
1A
#310000000
0!
03
#315000000
1!
1)
b0111 *
1+
13
1;
b0111 <
1=
b1000 >
0?
0A
#320000000
0!
03
#325000000
1!
1$
0%
0)
13
16
07
0;
#330000000
0!
03
#335000000
1!
11
02
13
#340000000
0!
03
#345000000
1!
0'
b1001 -
b1 /
12
13
09
#350000000
0!
03
#355000000
1!
b1010110101000000 ,
b1010 -
b10 /
02
13
#360000000
0!
03
#365000000
1!
1#
b1011 -
b11 /
01
13
15
#370000000
0!
03
#375000000
1!
0#
0$
1%
13
05
06
17
b0 >
#380000000
0!
03
#385000000
1!
1(
13
1:
1?
1@
#390000000
0!
03
#395000000
1!
0(
b1001 .
b10 /
00
13
08
0:
0@
1A
#400000000
0!
03
#405000000
1!
1(
1)
b0000 *
0+
13
1:
1;
b0000 <
0=
b1 >
1@
0A
#410000000
0!
03
#415000000
1!
0(
0)
b1010 .
b1 /
10
13
18
0:
0;
0@
1A
#420000000
0!
03
#425000000
1!
1(
1)
b0001 *
1+
13
1:
1;
b0001 <
1=
b10 >
1@
0A
#430000000
0!
03
#435000000
1!
1'
0(
0)
b1011 .
b0 /
00
13
08
19
0:
0;
0@
1A
#440000000
0!
03
#445000000
1!
1)
b0010 *
0+
13
1;
b0010 <
0=
b11 >
0?
0A
#450000000
0!
03
#455000000
1!
0)
13
0;
#460000000
0!
03
#465000000
1!
13
#470000000
0!
03
#475000000
1!
11
12
13
#480000000
0!
03
#485000000
1!
0'
b1010110101010000 ,
b1100 -
b1 /
01
13
09
#490000000
0!
03
#495000000
1!
1(
13
1:
1?
1@
#500000000
0!
03
#505000000
1!
1'
0(
b1100 .
b0 /
10
13
18
19
0:
0@
1A
#510000000
0!
03
#515000000
1!
1)
b0011 *
1+
13
1;
b0011 <
1=
b100 >
0?
0A
#520000000
0!
03
#525000000
1!
0)
11
02
13
0;
#530000000
0!
03
#535000000
1!
0'
b1101 -
b1 /
01
13
09
#540000000
0!
03
#545000000
1!
1(
13
1:
1?
1@
#550000000
0!
03
#555000000
1!
1'
0(
b1101 .
b0 /
00
13
08
19
0:
0@
1A
#560000000
0!
03
#565000000
1!
1)
b0100 *
0+
13
1;
b0100 <
0=
b101 >
0?
0A
#570000000
0!
03
#575000000
1!
0)
11
13
0;
#580000000
0!
03
#585000000
1!
0'
b1110 -
b1 /
01
13
09
#590000000
0!
03
#595000000
1!
1(
13
1:
1?
1@
#600000000
0!
03
#605000000
1!
1'
0(
b1110 .
b0 /
13
19
0:
0@
1A
#610000000
0!
03
#615000000
1!
1)
b0101 *
13
1;
b0101 <
b110 >
0?
0A
#620000000
0!
03
#625000000
1!
0)
11
12
13
0;
#630000000
0!
03
#635000000
1!
0'
b1010110101010010 ,
b1111 -
b1 /
01
13
09
#640000000
0!
03
#645000000
1!
1(
13
1:
1?
1@
#650000000
0!
03
#655000000
1!
1'
0(
b1111 .
b0 /
10
13
18
19
0:
0@
1A
#660000000
0!
03
#665000000
1!
1)
b0110 *
1+
13
1;
b0110 <
1=
b111 >
0?
0A
#670000000
0!
03
#675000000
1!
0)
11
02
13
0;
#680000000
0!
03
#685000000
1!
0'
b0 -
b1 /
01
13
09
#690000000
0!
03
#695000000
1!
1(
13
1:
1?
1@
#700000000
0!
03
#705000000
1!
1'
0(
b0 .
b0 /
00
13
08
19
0:
0@
1A
#710000000
0!
03
#715000000
1!
1)
b0111 *
0+
13
1;
b0111 <
0=
b1000 >
0?
0A
#720000000
0!
03
#725000000
1!
1$
0%
0)
13
16
07
0;
#730000000
0!
03
#735000000
1!
11
12
13
#740000000
0!
03
#745000000
1!
0'
b1 -
b1 /
02
13
09
#750000000
0!
03
#755000000
1!
b10 -
b10 /
12
13
#760000000
0!
03
#765000000
1!
b11 -
b11 /
02
13
#770000000
0!
03
#775000000
1!
b100 -
b100 /
12
13
#780000000
0!
03
#785000000
1!
b101 -
b101 /
13
#790000000
0!
03
#795000000
1!
b110 -
b110 /
02
13
#800000000
0!
03
#805000000
1!
b111 -
b111 /
12
13
#810000000
0!
03
#815000000
1!
1#
b1000 -
b1000 /
01
13
15
#820000000
0!
03
#825000000
1!
0#
0$
1%
13
05
06
17
b0 >
#830000000
0!
03
#835000000
1!
1(
13
1:
1?
1@
#840000000
0!
03
#845000000
1!
0(
b1 .
b111 /
10
13
18
0:
0@
1A
#850000000
0!
03
#855000000
1!
1(
1)
b0000 *
1+
13
1:
1;
b0000 <
1=
b1 >
1@
0A
#860000000
0!
03
#865000000
1!
0(
0)
b10 .
b110 /
00
13
08
0:
0;
0@
1A
#870000000
0!
03
#875000000
1!
1(
1)
b0001 *
0+
13
1:
1;
b0001 <
0=
b10 >
1@
0A
#880000000
0!
03
#885000000
1!
0(
0)
b11 .
b101 /
10
13
18
0:
0;
0@
1A
#890000000
0!
03
#895000000
1!
1(
1)
b0010 *
1+
13
1:
1;
b0010 <
1=
b11 >
1@
0A
#900000000
0!
03
#905000000
1!
0(
0)
b100 .
b100 /
00
13
08
0:
0;
0@
1A
#910000000
0!
03
#915000000
1!
1(
1)
b0011 *
0+
13
1:
1;
b0011 <
0=
b100 >
1@
0A
#920000000
0!
03
#925000000
1!
0(
0)
b101 .
b11 /
10
13
18
0:
0;
0@
1A
#930000000
0!
03
#935000000
1!
1(
1)
b0100 *
1+
13
1:
1;
b0100 <
1=
b101 >
1@
0A
#940000000
0!
03
#945000000
1!
0(
0)
b110 .
b10 /
13
0:
0;
0@
1A
#950000000
0!
03
#955000000
1!
1(
1)
b0101 *
13
1:
1;
b0101 <
b110 >
1@
0A
#960000000
0!
03
#965000000
1!
0(
0)
b111 .
b1 /
00
13
08
0:
0;
0@
1A
#970000000
0!
03
#975000000
1!
1(
1)
b0110 *
0+
13
1:
1;
b0110 <
0=
b111 >
1@
0A
#980000000
0!
03
#985000000
1!
1'
0(
0)
b1000 .
b0 /
10
13
18
19
0:
0;
0@
1A
#990000000
0!
03
#995000000
1!
1)
b0111 *
1+
13
1;
b0111 <
1=
b1000 >
0?
0A
#1000000000
0!
03
#1005000000
1!
1$
0%
0)
13
16
07
0;
